{
  "NDX": {
    "bt_accuracy": 0.4778,
    "bt_rolling_20": 0.55,
    "bt_rolling_50": 0.44,
    "bt_total": 90,
    "live_accuracy": null,
    "live_rolling_20": null,
    "live_rolling_50": null,
    "live_total": 0,
    "win_rate": 0.4778,
    "avg_win": 0.006299,
    "avg_loss": 0.006021
  },
  "TSX": {
    "bt_accuracy": 0.5811,
    "bt_rolling_20": 0.6,
    "bt_rolling_50": 0.56,
    "bt_total": 74,
    "live_accuracy": null,
    "live_rolling_20": null,
    "live_rolling_50": null,
    "live_total": 0,
    "win_rate": 0.5811,
    "avg_win": 0.004992,
    "avg_loss": 0.003605
  },
  "NIFTY": {
    "bt_accuracy": 0.5244,
    "bt_rolling_20": 0.55,
    "bt_rolling_50": 0.52,
    "bt_total": 82,
    "live_accuracy": null,
    "live_rolling_20": null,
    "live_rolling_50": null,
    "live_total": 0,
    "win_rate": 0.5244,
    "avg_win": 0.005759,
    "avg_loss": 0.004299
  },
  "GOLD": {
    "bt_accuracy": 0.4694,
    "bt_rolling_20": 0.4,
    "bt_rolling_50": 0.42,
    "bt_total": 98,
    "live_accuracy": null,
    "live_rolling_20": null,
    "live_rolling_50": null,
    "live_total": 0,
    "win_rate": 0.4694,
    "avg_win": 0.006742,
    "avg_loss": 0.005199
  },
  "CRUDE": {
    "bt_accuracy": 0.5765,
    "bt_rolling_20": 0.55,
    "bt_rolling_50": 0.62,
    "bt_total": 85,
    "live_accuracy": null,
    "live_rolling_20": null,
    "live_rolling_50": null,
    "live_total": 0,
    "win_rate": 0.5765,
    "avg_win": 0.01527,
    "avg_loss": 0.020707
  },
  "NATGAS": {
    "bt_accuracy": 0.4578,
    "bt_rolling_20": 0.55,
    "bt_rolling_50": 0.48,
    "bt_total": 83,
    "live_accuracy": null,
    "live_rolling_20": null,
    "live_rolling_50": null,
    "live_total": 0,
    "win_rate": 0.4578,
    "avg_win": 0.00909,
    "avg_loss": 0.010842
  },
  "_updated": "2026-04-20T20:12:05.218808+00:00"
}